{
  "symbol": "EURUSD",
  "timeframe": "5m",
  "timestamp_utc": "2025-12-02T14:00:00+00:00",
  "signal": "HOLD",
  "confidence": 0,
  "entry": null,
  "stop": null,
  "targets": [],
  "rationale": "Current market price is 1.16183. Without the RSI indicator available, price action does not suggest a clear overbought or oversold condition. Given that there are no clear signals to act within the current range and data context, I'm suggesting to HOLD.",
  "invalidation": "Look for a shift towards a clearer signal either above the 1.16280 resistance or below the 1.16000 support to reassess.",
  "prompt_name": "prompt4",
  "raw_notes": "",
  "current_price": 1.16183,
  "entry_distance_pips": null,
  "validation": {
    "valid": true,
    "original_signal": "HOLD",
    "final_signal": "HOLD",
    "violation_reason": null,
    "entry_distance_pips": null,
    "current_price": 1.16183,
    "warnings": []
  }
}