{
  "symbol": "EURUSD",
  "timeframe": "5m",
  "timestamp_utc": "2025-12-18T14:00:00+00:00",
  "signal": "BUY",
  "confidence": 0.7,
  "entry": 1.175,
  "stop": 1.1735,
  "targets": [
    1.1765,
    1.1775
  ],
  "rationale": "The EURUSD is showing signs of bullish momentum, with recent price action indicating support around the current level. A slight upward trend is observed in the 5m timeframe, suggesting a buying opportunity. Market sentiment appears positive based on the latest news and economic data releases.",
  "invalidation": "If the price drops below 1.17350, the bullish premise would be invalidated, indicating potential reversal.",
  "prompt_name": "prompt2",
  "raw_notes": "",
  "current_price": 1.17488,
  "entry_distance_pips": 0.01,
  "validation": {
    "valid": true,
    "original_signal": "BUY",
    "final_signal": "BUY",
    "violation_reason": null,
    "entry_distance_pips": 0.01,
    "current_price": 1.17488,
    "warnings": []
  }
}